upgradeable_contract/__init__.py
upgradeable_contract/contract.py
upgradeable_contract/contracts/ProxyAdmin.json
upgradeable_contract/contracts/TransparentUpgradeableProxy.json
upgradeable_contract/types.py
upgradeable_contract/utils.py
web3_upgradeable_proxy-0.1.0.dist-info/METADATA
web3_upgradeable_proxy-0.1.0.dist-info/WHEEL
web3_upgradeable_proxy-0.1.0.dist-info/LICENSE
web3_upgradeable_proxy-0.1.0.dist-info/RECORD
