Metadata-Version: 2.1
Name: web3-upgradeable-proxy
Version: 0.1.0
Summary: Deploy contract with transparent upgradeable proxy schema
Home-page: https://github.com/tinom9/web3-upgradeable-contract
License: MIT
Author: Tino Martínez Molina
Author-email: tino@martinezmolina.es
Requires-Python: >=3.10,<4.0
Classifier: License :: OSI Approved :: MIT License
Classifier: Programming Language :: Python :: 3
Classifier: Programming Language :: Python :: 3.10
Classifier: Programming Language :: Python :: 3.11
Requires-Dist: web3 (>=6.0.0,<7.0.0)
